movinglines/ArcticTable_Current.txt
movinglines/Canadian_classF_Airspaces.kmz
movinglines/EarthCARE.tle
movinglines/GFS_interp_utils.py
movinglines/MSS.txt
movinglines/MovingLines_QuickGuide.pdf
movinglines/README.md
movinglines/WMS.txt
movinglines/__init__.py
movinglines/aeronet.py
movinglines/aeronet_locations.old.txt
movinglines/aeronet_locations.txt
movinglines/aeronet_locations_full.txt
movinglines/aeronet_sites.kmz
movinglines/app_tester.py
movinglines/arc.ico
movinglines/buoys.txt
movinglines/buoys_utils.py
movinglines/elevation_10KMmd_GMTEDmd.tif
movinglines/excel_interface.py
movinglines/firs.kmz
movinglines/flightnav_utils.py
movinglines/gui.py
movinglines/gui_plot.py
movinglines/image_corners.json
movinglines/image_corners_tidbits.json
movinglines/iwg_1319.txt
movinglines/iwg_1320.txt
movinglines/labels.bak.txt
movinglines/labels.txt
movinglines/labels_old.txt
movinglines/license.txt
movinglines/load_utils.py
movinglines/map_interactive.py
movinglines/map_tester.py
movinglines/map_utils.py
movinglines/ml.py
movinglines/nat_decode.py
movinglines/pace.tle
movinglines/platform.txt
movinglines/plot_canadian_airspace.py
movinglines/profiles.txt
movinglines/sat.json
movinglines/sat.tle
movinglines/version.py
movinglines/vert_wms.txt
movinglines/write_utils.py
movinglines/xlwings_pyonly_backup.py
movinglines/flt_module/ARCSIX_Braster.flt
movinglines/flt_module/ARCSIX_G3_bowling_alley.flt
movinglines/flt_module/ARCSIX_G3_bowling_alley.png
movinglines/flt_module/ARCSIX_P3_Bowling_alley.flt
movinglines/flt_module/ARCSIX_P3_Bowling_alley.png
movinglines/flt_module/ARCSIX_P3_Helix.flt
movinglines/flt_module/Cloud_BB_sawtooth.flt
movinglines/flt_module/Cloud_BB_sawtooth.png
movinglines/flt_module/IMPACTS_5-Point_Leg.flt
movinglines/flt_module/IMPACTS_5-Point_Leg.png
movinglines/flt_module/IMPACTS_lawnmower_ER2.flt
movinglines/flt_module/IMPACTS_lawnmower_ER2.png
movinglines/flt_module/IMPACTS_lawnmower_ER2_default.flt
movinglines-1.63.dist-info/METADATA
movinglines-1.63.dist-info/WHEEL
movinglines-1.63.dist-info/entry_points.txt
movinglines-1.63.dist-info/namespace_packages.txt
movinglines-1.63.dist-info/top_level.txt
movinglines-1.63.dist-info/RECORD
