Metadata-Version: 2.4
Name: movinglines
Version: 1.63
Summary: Moving Lines - Research flight planner
Home-page: https://github.com/samuelleblanc/fp
Author: Samuel LeBlanc
Author-email: samuel.leblanc@nasa.gov
Maintainer: Samuel LeBlanc
Maintainer-email: samuel.leblanc@nasa.gov
License: GPL-3.0
Keywords: ml
Platform: any
Classifier: Intended Audience :: Science/Research
Classifier: Development Status :: 5 - Production/Stable
Classifier: Programming Language :: Python :: 3
Requires-Dist: numpy
Requires-Dist: geopy
Requires-Dist: scipy
Requires-Dist: pyephem
Requires-Dist: Pillow
Requires-Dist: cartopy<0.20.1
Requires-Dist: shapely<2.0.0
Requires-Dist: pykml
Requires-Dist: rasterio
Requires-Dist: gpxpy
Requires-Dist: bs4
Requires-Dist: xlwings
Requires-Dist: json_tricks
Requires-Dist: simplekml
Requires-Dist: matplotlib<3.6.0
Requires-Dist: owslib
Requires-Dist: ipdb
Requires-Dist: flightplandb
Requires-Dist: pytz
Requires-Dist: pandas
Dynamic: author
Dynamic: author-email
Dynamic: classifier
Dynamic: description
Dynamic: description-content-type
Dynamic: home-page
Dynamic: keywords
Dynamic: license
Dynamic: maintainer
Dynamic: maintainer-email
Dynamic: platform
Dynamic: requires-dist
Dynamic: summary
